mcp_on_demand_tools/__init__.py
mcp_on_demand_tools/server.py
mcp_on_demand_tools/recipes/render_template.yaml
mcp_on_demand_tools-0.1.2.dist-info/METADATA
mcp_on_demand_tools-0.1.2.dist-info/WHEEL
mcp_on_demand_tools-0.1.2.dist-info/entry_points.txt
mcp_on_demand_tools-0.1.2.dist-info/licenses/LICENSE
mcp_on_demand_tools-0.1.2.dist-info/RECORD
