Metadata-Version: 2.4
Name: mcp-on-demand-tools
Version: 0.1.2
Summary: An MCP server for dynamic tool registration and AI-powered simulation via Goose recipes
Author-email: Aaron Goldsmith <aargoldsmith@gmail.com>
License-File: LICENSE
Requires-Python: >=3.12
Requires-Dist: mcp>=1.17.0
